<?xml version="1.0" encoding="utf-8" ?>
<dwsync>
<file name="advisor-notes.asp" server="//Pacer-Bravo/Projects/Web_Sites/newPACER/" local="131262990350000000" remote="131262990350000000" Dst="2" />
<file name="evaluations.asp" server="//Pacer-Bravo/Projects/Web_Sites/newPACER/" local="131262990350000000" remote="131262990350000000" Dst="2" />
<file name="faqs.asp" server="//Pacer-Bravo/Projects/Web_Sites/newPACER/" local="131262990350000000" remote="131262990350000000" Dst="2" />
<file name="index-login.asp" server="//Pacer-Bravo/Projects/Web_Sites/newPACER/" local="131262990350000000" remote="131262990350000000" Dst="2" />
<file name="index.asp" server="//Pacer-Bravo/Projects/Web_Sites/newPACER/" local="131262990350000000" remote="131262990350000000" Dst="2" />
<file name="loginnav.html" server="//Pacer-Bravo/Projects/Web_Sites/newPACER/" local="130440465820000000" remote="130440465820000000" Dst="2" />
<file name="logintemplate.asp" server="//Pacer-Bravo/Projects/Web_Sites/newPACER/" local="131262990350000000" remote="131262990350000000" Dst="2" />
<file name="logintopnav.html" server="//Pacer-Bravo/Projects/Web_Sites/newPACER/" local="130244436610000000" remote="130244436610000000" Dst="2" />
<file name="resources.asp" server="//Pacer-Bravo/Projects/Web_Sites/newPACER/" local="131304488270000000" remote="131304488270000000" Dst="2" />
</dwsync>