<?xml version="1.0" encoding="utf-8" ?>
<dwsync>
<file name="2-col-template.asp" server="//Pacer-Bravo/Projects/Web_Sites/newPACER/" local="130210670380000000" remote="130210670380000000" Dst="2" />
<file name="3-col-template.asp" server="//Pacer-Bravo/Projects/Web_Sites/newPACER/" local="130210670610000000" remote="130210670610000000" Dst="2" />
<file name="anna-richey.asp" server="//Pacer-Bravo/Projects/Web_Sites/newPACER/" local="131098856260000000" remote="131098856260000000" Dst="2" />
<file name="because-these-kids-are.asp" server="//Pacer-Bravo/Projects/Web_Sites/newPACER/" local="131098856700000000" remote="131098856700000000" Dst="2" />
<file name="butterfly.asp" server="//Pacer-Bravo/Projects/Web_Sites/newPACER/" local="131098857060000000" remote="131098857060000000" Dst="2" />
<file name="hayley-reardon-music.asp" server="//Pacer-Bravo/Projects/Web_Sites/newPACER/" local="131314931260000000" remote="131314931260000000" Dst="2" />
<file name="index.asp" server="//Pacer-Bravo/Projects/Web_Sites/newPACER/" local="131098855950000000" remote="131098855950000000" Dst="2" />
<file name="jetset-getset.asp" server="//Pacer-Bravo/Projects/Web_Sites/newPACER/" local="131409074770000000" remote="131409074770000000" Dst="2" />
<file name="ls-temp.asp" server="//Pacer-Bravo/Projects/Web_Sites/newPACER/" local="130214094840000000" remote="130214094840000000" Dst="2" />
<file name="marinav.asp" server="//Pacer-Bravo/Projects/Web_Sites/newPACER/" local="131098858210000000" remote="131098858210000000" Dst="2" />
<file name="strain.asp" server="//Pacer-Bravo/Projects/Web_Sites/newPACER/" local="131098858460000000" remote="131098858460000000" Dst="2" />
<file name="taylor-silent-voices.asp" server="//Pacer-Bravo/Projects/Web_Sites/newPACER/" local="131098858820000000" remote="131098858820000000" Dst="2" />
</dwsync>