<?xml version="1.0" encoding="utf-8" ?>
<dwsync>
<file name="dialog-alt.html" server="//Pacer-Bravo/Projects/Web_Sites/newPACER/" local="130380715300000000" remote="130380715300000000" Dst="2" />
<file name="dialog-buttons.html" server="//Pacer-Bravo/Projects/Web_Sites/newPACER/" local="130380715300000000" remote="130380715300000000" Dst="2" />
<file name="dialog-corners.html" server="//Pacer-Bravo/Projects/Web_Sites/newPACER/" local="130380715300000000" remote="130380715300000000" Dst="2" />
<file name="dialog-noclosebtn.html" server="//Pacer-Bravo/Projects/Web_Sites/newPACER/" local="130380715300000000" remote="130380715300000000" Dst="2" />
<file name="dialog-overlay.html" server="//Pacer-Bravo/Projects/Web_Sites/newPACER/" local="130380715300000000" remote="130380715300000000" Dst="2" />
<file name="dialog-rightclosebtn.html" server="//Pacer-Bravo/Projects/Web_Sites/newPACER/" local="130380715300000000" remote="130380715300000000" Dst="2" />
<file name="dialog-success.html" server="//Pacer-Bravo/Projects/Web_Sites/newPACER/" local="130380715300000000" remote="130380715300000000" Dst="2" />
<file name="dialog-with-select.html" server="//Pacer-Bravo/Projects/Web_Sites/newPACER/" local="130380715300000000" remote="130380715300000000" Dst="2" />
<file name="dialog.html" server="//Pacer-Bravo/Projects/Web_Sites/newPACER/" local="130380715300000000" remote="130380715300000000" Dst="2" />
<file name="index.html" server="//Pacer-Bravo/Projects/Web_Sites/newPACER/" local="130380715300000000" remote="130380715300000000" Dst="2" />
</dwsync>